cmake_init_lib/__init__.py
cmake_init_lib/__main__.py
cmake_init_lib/cmake-init.zip
cmake_init_lib/cmake_init.py
cmake_init_lib/template.py
cmake_init-0.41.0.dist-info/METADATA
cmake_init-0.41.0.dist-info/WHEEL
cmake_init-0.41.0.dist-info/entry_points.txt
cmake_init-0.41.0.dist-info/top_level.txt
cmake_init-0.41.0.dist-info/RECORD
