Metadata-Version: 2.1
Name: cmake-init
Version: 0.41.0
Summary: The missing CMake project initializer
Home-page: https://github.com/friendlyanon/cmake-init
Author: friendlyanon
Author-email: friendlyanon_@hotmail.com
License: GPLv3+
Platform: OS Independent
Classifier: Development Status :: 4 - Beta
Classifier: Environment :: Console
Classifier: Intended Audience :: Developers
Classifier: License :: OSI Approved :: GNU General Public License v3 (GPLv3)
Classifier: Operating System :: OS Independent
Classifier: Programming Language :: C
Classifier: Programming Language :: C++
Classifier: Programming Language :: Python :: 3
Classifier: Topic :: Software Development :: Build Tools
Classifier: Topic :: Utilities
Requires-Python: >=3.8
